django_access_point/__init__.py
django_access_point/app_auth.py
django_access_point/app_create_portal_admin_user.py
django_access_point/app_models.py
django_access_point/app_password_reset_email.html
django_access_point/app_profile_invite_email.html
django_access_point/app_serializers.py
django_access_point/app_urls.py
django_access_point/app_views.py
django_access_point/excel_report.py
django_access_point/utils.py
django_access_point/utils_response.py
django_access_point/management/__init__.py
django_access_point/management/commands/__init__.py
django_access_point/management/commands/createapp.py
django_access_point/mixins/__init__.py
django_access_point/mixins/user.py
django_access_point/models/__init__.py
django_access_point/models/custom_field.py
django_access_point/models/user.py
django_access_point/serializers/__init__.py
django_access_point/serializers/auth.py
django_access_point/serializers/crud.py
django_access_point/serializers/custom_field.py
django_access_point/serializers/validations/__init__.py
django_access_point/serializers/validations/validate.py
django_access_point/serializers/validations/validation_rule_schema.py
django_access_point/views/__init__.py
django_access_point/views/crud.py
django_access_point/views/custom_field.py
django_access_point/views/helpers_crud.py
django_access_point-0.0.31.dist-info/METADATA
django_access_point-0.0.31.dist-info/WHEEL
django_access_point-0.0.31.dist-info/top_level.txt
django_access_point-0.0.31.dist-info/RECORD
