Metadata-Version: 2.1
Name: django-access-point
Version: 0.0.31
Summary: Django Access Point is a package designed to streamline the creation of APIs for user and role management in SaaS projects. It simplifies user authentication, authorization, and role-based access control, enabling developers to build robust and scalable applications with ease. Additionally, this package supports custom fields, allowing users to manage their own specific fields for enhanced flexibility and customization.
Author: Karthick Sivakumar
Author-email: karthicksivakumardev@gmail.com
Requires-Dist: Django>=3.0.0
Requires-Dist: django-cors-headers>=4.4.0
Requires-Dist: djangorestframework>=3.0.0
Requires-Dist: djangorestframework-simplejwt>=5.3.0
Requires-Dist: jsonschema>=4.17.0
Requires-Dist: openpyxl==3.1.5
